tpds/__init__.py
tpds/licenses.txt
tpds/app/TPDS_Application.py
tpds/app/__init__.py
tpds/app/app.py
tpds/app/check_updates.py
tpds/app/control.py
tpds/app/docks.py
tpds/app/main.py
tpds/app/network.py
tpds/app/processing.py
tpds/app/tools.py
tpds/app/vars.py
tpds/app/worker.py
tpds/app/assets/Trust Platform.icns
tpds/app/assets/app.ico
tpds/app/assets/icons8-close_window.png
tpds/app/assets/icons8-dev.png
tpds/app/messages/__init__.py
tpds/app/messages/app_messages.py
tpds/app/messages/msg_handler_tflx.py
tpds/app/messages/provision_user_inputs.py
tpds/app/messages/tflx_provisioning_xml_ui.py
tpds/app/ui/__init__.py
tpds/app/ui/packman_form.py
tpds/app/ui/packman_form.ui
tpds/app/ui/packman_ui.py
tpds/app/ui/settings_dialog.py
tpds/app/ui/settings_dialog.ui
tpds/app/ui/settings_ui.py
tpds_application-2.3.18.dist-info/LICENSE
tpds_application-2.3.18.dist-info/METADATA
tpds_application-2.3.18.dist-info/WHEEL
tpds_application-2.3.18.dist-info/entry_points.txt
tpds_application-2.3.18.dist-info/top_level.txt
tpds_application-2.3.18.dist-info/RECORD
