Metadata-Version: 2.1
Name: tpds-application
Version: 2.3.18
Summary: Microchip(SPG) Trust Platform Standalone Application
Maintainer-email: Microchip Technology <SPG.Tools@microchip.com>
License: (c) 2023 Microchip Technology Inc. and its subsidiaries.
Classifier: License :: Other/Proprietary License
Classifier: Development Status :: 4 - Beta
Classifier: Programming Language :: Python :: 3
Classifier: Operating System :: OS Independent
Requires-Python: >=3.8
License-File: LICENSE
Requires-Dist: tpds-core>=2.3.18
Requires-Dist: tpds-helper>=2.3.14
Requires-Dist: tpds-boards>=2.2.10
Requires-Dist: Markdown
Requires-Dist: packaging
Requires-Dist: PySide6<=6.6.2
Requires-Dist: requests
Provides-Extra: ext
Requires-Dist: tpds-extension-aes-message-encryption; extra == "ext"
Requires-Dist: tpds-extension-avnet-iotconnect; extra == "ext"
Requires-Dist: tpds-extension-cec17xx-support; extra == "ext"
Requires-Dist: tpds-extension-cryptoquantique-quarklink; extra == "ext"
Requires-Dist: tpds-extension-dspic33-support; extra == "ext"
Requires-Dist: tpds-extension-ecc204-support; extra == "ext"
Requires-Dist: tpds-extension-ecc608-sip-support; extra == "ext"
Requires-Dist: tpds-extension-keystream-connect; extra == "ext"
Requires-Dist: tpds-extension-secureboot; extra == "ext"
Requires-Dist: tpds-extension-sha104-105-support; extra == "ext"
Requires-Dist: tpds-extension-spg-asym-auth; extra == "ext"
Requires-Dist: tpds-extension-spg-cloud-connect[all]; extra == "ext"
Requires-Dist: tpds-extension-spg-fw-validation; extra == "ext"
Requires-Dist: tpds-extension-spg-ip-protection; extra == "ext"
Requires-Dist: tpds-extension-spg-public-key-rotation; extra == "ext"
Requires-Dist: tpds-extension-spg-symmetric-auth; extra == "ext"
Requires-Dist: tpds-extension-ta010-support; extra == "ext"
Requires-Dist: tpds-extension-wpc-transmitter; extra == "ext"
Provides-Extra: dev
Requires-Dist: flake8; extra == "dev"
Requires-Dist: black; extra == "dev"
Requires-Dist: isort; extra == "dev"
Requires-Dist: mypy; extra == "dev"
Provides-Extra: test
Requires-Dist: responses==0.23.1; extra == "test"
Requires-Dist: pytest-cov; extra == "test"
Requires-Dist: pytest-mock; extra == "test"
Requires-Dist: pytest-integration; extra == "test"
